{"1":{"id":1,"region":{"he":"גולן","en":"Golan"},"name":{"he":"גולן 1","en":"Golan 1"},"coverTime":0,"locations":[70,175,250,1020,1099,1204,1283,1436],"geometry":{"bounds":{"northeast":{"lat":33.1827811,"lng":35.8084861},"southwest":{"lat":33.260472,"lng":35.720421}},"location":{"lat":33.221626549999996,"lng":35.76445355}}},"2":{"id":2,"region":{"he":"גולן","en":"Golan"},"name":{"he":"גולן 2","en":"Golan 2"},"coverTime":0,"locations":[60,101,186,209,373,472,530,723,728,910,1008,1067,1184,1198,1250,1694],"geometry":{"bounds":{"northeast":{"lat":32.742441,"lng":35.812959},"southwest":{"lat":32.8486699,"lng":35.651754}},"location":{"lat":32.795555449999995,"lng":35.732356499999995}}},"3":{"id":3,"region":{"he":"גולן","en":"Golan"},"name":{"he":"גולן 3","en":"Golan 3"},"coverTime":0,"locations":[94,183,791,1152,1417,1627],"geometry":{"bounds":{"northeast":{"lat":32.9413071,"lng":35.841708},"southwest":{"lat":33.129081,"lng":35.7543521}},"location":{"lat":33.03519405,"lng":35.798030049999994}}},"7":{"id":7,"region":{"he":"קצרין","en":"Golan"},"name":{"he":"קצרין 7","en":"Golan 7"},"coverTime":15,"locations":[14,204,684,863,1115,1575,1596,1602,1781],"geometry":{"bounds":{"northeast":{"lat":32.874518,"lng":35.746659},"southwest":{"lat":33.127925,"lng":35.6342129}},"location":{"lat":33.0012215,"lng":35.69043595}}},"10":{"id":10,"region":{"he":"קצרין","en":"Golan"},"name":{"he":"קצרין 10","en":"Golan 10"},"coverTime":15,"locations":[588,1093,1103,1405,1679,1784,1820],"geometry":{"bounds":{"northeast":{"lat":32.686265,"lng":35.6730789},"southwest":{"lat":32.8398211,"lng":35.594384}},"location":{"lat":32.76304305,"lng":35.63373145}}},"14":{"id":14,"region":{"he":"קו העימות","en":"Frontline"},"name":{"he":"קו העימות 14","en":"Frontline 14"},"coverTime":0,"locations":[385,954,998,1135,1770],"geometry":{"bounds":{"northeast":{"lat":33.066831,"lng":35.1643561},"southwest":{"lat":33.081814,"lng":35.103829}},"location":{"lat":33.0743225,"lng":35.13409255}}},"15":{"id":15,"region":{"he":"קו העימות","en":"Frontline"},"name":{"he":"קו העימות 15","en":"Frontline 15"},"coverTime":0,"locations":[12,66,114,118,425,491,492,725,813,1480],"geometry":{"bounds":{"northeast":{"lat":33.05988,"lng":35.253144},"southwest":{"lat":33.083608,"lng":35.1663139}},"location":{"lat":33.071743999999995,"lng":35.20972895}}},"16":{"id":16,"region":{"he":"קו העימות","en":"Frontline"},"name":{"he":"קו העימות 16","en":"Frontline 16"},"coverTime":0,"locations":[57,647,1747,1798],"geometry":{"bounds":{"northeast":{"lat":33.0769619,"lng":35.321565},"southwest":{"lat":33.0974051,"lng":35.2778931}},"location":{"lat":33.0871835,"lng":35.299729049999996}}},"17":{"id":17,"region":{"he":"קו העימות","en":"Frontline"},"name":{"he":"קו העימות 17","en":"Frontline 17"},"coverTime":0,"locations":[55,198,1249,1523],"geometry":{"bounds":{"northeast":{"lat":33.0370231,"lng":35.331397},"southwest":{"lat":33.061502,"lng":35.28209}},"location":{"lat":33.049262549999995,"lng":35.306743499999996}}},"19":{"id":19,"region":{"he":"קו העימות","en":"Frontline"},"name":{"he":"קו העימות 19","en":"Frontline 19"},"coverTime":0,"locations":[547,1182,1307],"geometry":{"bounds":{"northeast":{"lat":33.031415,"lng":35.413676},"southwest":{"lat":33.047135,"lng":35.353675}},"location":{"lat":33.039275,"lng":35.3836755}}},"20":{"id":20,"region":{"he":"קו העימות","en":"Frontline"},"name":{"he":"קו העימות 20","en":"Frontline 20"},"coverTime":0,"locations":[706,1527,1528,1542,1556],"geometry":{"bounds":{"northeast":{"lat":32.9888419,"lng":35.422268},"southwest":{"lat":33.0234789,"lng":35.302924}},"location":{"lat":33.0061604,"lng":35.362595999999996}}},"22":{"id":22,"region":{"he":"קו העימות","en":"Frontline"},"name":{"he":"קו העימות 22","en":"Frontline 22"},"coverTime":0,"locations":[50,398,822],"geometry":{"bounds":{"northeast":{"lat":33.061643,"lng":35.47819},"southwest":{"lat":33.084022,"lng":35.429926}},"location":{"lat":33.0728325,"lng":35.454058}}},"23":{"id":23,"region":{"he":"קו העימות","en":"Frontline"},"name":{"he":"קו העימות 23","en":"Frontline 23"},"coverTime":0,"locations":[433,581,968,1450,1669],"geometry":{"bounds":{"northeast":{"lat":33.0213389,"lng":35.507402},"southwest":{"lat":33.045656,"lng":35.406582}},"location":{"lat":33.03349745,"lng":35.456992}}},"24":{"id":24,"region":{"he":"קו העימות","en":"Frontline"},"name":{"he":"קו העימות 24","en":"Frontline 24"},"coverTime":0,"locations":[579,817,1081,1158,1683],"geometry":{"bounds":{"northeast":{"lat":33.0878461,"lng":35.556979},"southwest":{"lat":33.123558,"lng":35.505614}},"location":{"lat":33.105702050000005,"lng":35.531296499999996}}},"25":{"id":25,"region":{"he":"קו העימות","en":"Frontline"},"name":{"he":"קו העימות 25","en":"Frontline 25"},"coverTime":0,"locations":[490,878,935,989,1186,1458,1728,1773],"geometry":{"bounds":{"northeast":{"lat":33.1299071,"lng":35.664947},"southwest":{"lat":33.189951,"lng":35.590805}},"location":{"lat":33.15992905,"lng":35.627876}}},"26":{"id":26,"region":{"he":"קו העימות","en":"Frontline"},"name":{"he":"קו העימות 26","en":"Frontline 26"},"coverTime":0,"locations":[300,788,886,1060,1089,1108,1150,1165,1623,1815],"geometry":{"bounds":{"northeast":{"lat":33.201769,"lng":35.615216},"southwest":{"lat":33.2476911,"lng":35.539415}},"location":{"lat":33.22473005,"lng":35.5773155}}},"28":{"id":28,"region":{"he":"קו העימות","en":"Frontline"},"name":{"he":"קו העימות 28","en":"Frontline 28"},"coverTime":0,"locations":[583,585,591,1345,1708,1778],"geometry":{"bounds":{"northeast":{"lat":33.2246419,"lng":35.682365},"southwest":{"lat":33.261159,"lng":35.6172271}},"location":{"lat":33.24290045,"lng":35.64979605}}},"29":{"id":29,"region":{"he":"קו העימות","en":"Frontline"},"name":{"he":"קו העימות 29","en":"Frontline 29"},"coverTime":0,"locations":[532,1197,1336,1354,1711],"geometry":{"bounds":{"northeast":{"lat":32.9883128,"lng":35.1916791},"southwest":{"lat":33.0335189,"lng":35.0783227}},"location":{"lat":33.01091585,"lng":35.1350009}}},"30":{"id":30,"region":{"he":"קו העימות","en":"Frontline"},"name":{"he":"קו העימות 30","en":"Frontline 30"},"coverTime":0,"locations":[366,837],"geometry":{"bounds":{"northeast":{"lat":33.013362,"lng":35.155948},"southwest":{"lat":33.016878,"lng":35.111709}},"location":{"lat":33.015119999999996,"lng":35.1338285}}},"31":{"id":31,"region":{"he":"קו העימות","en":"Frontline"},"name":{"he":"קו העימות 31","en":"Frontline 31"},"coverTime":0,"locations":[527,797,1085,1211,1352,1425],"geometry":{"bounds":{"northeast":{"lat":33.001382,"lng":35.235332},"southwest":{"lat":33.044036,"lng":35.171573}},"location":{"lat":33.022709,"lng":35.2034525}}},"32":{"id":32,"region":{"he":"קו העימות","en":"Frontline"},"name":{"he":"קו העימות 32","en":"Frontline 32"},"coverTime":0,"locations":[603,701,900,1107,1110,1123],"geometry":{"bounds":{"northeast":{"lat":33.00348,"lng":35.30292},"southwest":{"lat":33.032696,"lng":35.237481}},"location":{"lat":33.018088000000006,"lng":35.2702005}}},"35":{"id":35,"region":{"he":"גליל עליון","en":"Golan"},"name":{"he":"גליל עליון 35","en":"Golan 35"},"coverTime":30,"locations":[995,1053,1648],"geometry":{"bounds":{"northeast":{"lat":32.967267,"lng":35.104881},"southwest":{"lat":32.9804449,"lng":35.0938451}},"location":{"lat":32.97385595,"lng":35.09936305}}},"37":{"id":37,"region":{"he":"גליל עליון","en":"Golan"},"name":{"he":"גליל עליון 37","en":"Golan 37"},"coverTime":30,"locations":[248,301,416,928,1285,1300,1411,1446,1762,1775],"geometry":{"bounds":{"northeast":{"lat":32.8952751,"lng":35.153891},"southwest":{"lat":32.989177,"lng":35.0658751}},"location":{"lat":32.94222605,"lng":35.10988305}}},"38":{"id":38,"region":{"he":"גליל עליון","en":"Golan"},"name":{"he":"גליל עליון 38","en":"Golan 38"},"coverTime":30,"locations":[229,422,503,757,828,857,912,1001,1460],"geometry":{"bounds":{"northeast":{"lat":32.9310739,"lng":35.2655879},"southwest":{"lat":32.9744461,"lng":35.148767}},"location":{"lat":32.95276,"lng":35.20717745}}},"40":{"id":40,"region":{"he":"גליל עליון","en":"Golan"},"name":{"he":"גליל עליון 40","en":"Golan 40"},"coverTime":30,"locations":[856,1517,1802],"geometry":{"bounds":{"northeast":{"lat":32.93041,"lng":35.2549759},"southwest":{"lat":32.942475,"lng":35.2320839}},"location":{"lat":32.9364425,"lng":35.2435299}}},"41":{"id":41,"region":{"he":"גליל עליון","en":"Golan"},"name":{"he":"גליל עליון 41","en":"Golan 41"},"coverTime":30,"locations":[768,854,1026],"geometry":{"bounds":{"northeast":{"lat":32.982375,"lng":35.3195851},"southwest":{"lat":32.967916,"lng":35.207723}},"location":{"lat":32.975145499999996,"lng":35.26365405}}},"42":{"id":42,"region":{"he":"גליל עליון","en":"Golan"},"name":{"he":"גליל עליון 42","en":"Golan 42"},"coverTime":30,"locations":[267,498,556,977,985,1018,1245,1303,1401,1557,1579,1631,1716,1755],"geometry":{"bounds":{"northeast":{"lat":32.908011,"lng":35.4162369},"southwest":{"lat":32.939461,"lng":35.184593}},"location":{"lat":32.923736000000005,"lng":35.300414950000004}}},"43":{"id":43,"region":{"he":"גליל עליון","en":"Golan"},"name":{"he":"גליל עליון 43","en":"Golan 43"},"coverTime":30,"locations":[292,713,741],"geometry":{"bounds":{"northeast":{"lat":32.952963,"lng":35.4004239},"southwest":{"lat":32.952298,"lng":35.30878000000001}},"location":{"lat":32.9526305,"lng":35.35460195}}},"44":{"id":44,"region":{"he":"גליל עליון","en":"Golan"},"name":{"he":"גליל עליון 44","en":"Golan 44"},"coverTime":30,"locations":[87,201,389,721,958,1069,1157,1426,1531,1573,1790],"geometry":{"bounds":{"northeast":{"lat":32.934353,"lng":35.463122},"southwest":{"lat":33.0018471,"lng":35.430013}},"location":{"lat":32.968100050000004,"lng":35.4465675}}},"46":{"id":46,"region":{"he":"גליל עליון","en":"Golan"},"name":{"he":"גליל עליון 46","en":"Golan 46"},"coverTime":30,"locations":[1340],"geometry":{"bounds":{"northeast":{"lat":33.0173121,"lng":35.445586},"southwest":{"lat":33.0040649,"lng":35.4312081}},"location":{"lat":33.0106885,"lng":35.43839705}}},"47":{"id":47,"region":{"he":"גליל עליון","en":"Golan"},"name":{"he":"גליל עליון 47","en":"Golan 47"},"coverTime":30,"locations":[116,486,699,806,1172,1452,1719],"geometry":{"bounds":{"northeast":{"lat":33.000981,"lng":35.638195},"southwest":{"lat":33.0476739,"lng":35.522549}},"location":{"lat":33.02432745,"lng":35.580372}}},"49":{"id":49,"region":{"he":"גליל עליון","en":"Golan"},"name":{"he":"גליל עליון 49","en":"Golan 49"},"coverTime":30,"locations":[274,1563],"geometry":{"bounds":{"northeast":{"lat":32.984376,"lng":35.537904},"southwest":{"lat":32.9740559,"lng":35.45507}},"location":{"lat":32.97921595,"lng":35.496487}}},"50":{"id":50,"region":{"he":"גליל עליון","en":"Golan"},"name":{"he":"גליל עליון 50","en":"Golan 50"},"coverTime":30,"locations":[189,193,202,620,734,744,849,894,932,966,967,1058,1455,1641],"geometry":{"bounds":{"northeast":{"lat":32.906485,"lng":35.6110359},"southwest":{"lat":32.985216,"lng":35.52183309999999}},"location":{"lat":32.945850500000006,"lng":35.56643449999999}}},"55":{"id":55,"region":{"he":"גליל תחתון","en":"Golan"},"name":{"he":"גליל תחתון 55","en":"Golan 55"},"coverTime":60,"locations":[214,500,704,717,850,903,905,987,1023,1647],"geometry":{"bounds":{"northeast":{"lat":32.806537,"lng":35.5299829},"southwest":{"lat":32.886168,"lng":35.454502}},"location":{"lat":32.846352499999995,"lng":35.49224245}}},"56":{"id":56,"region":{"he":"גליל תחתון","en":"Golan"},"name":{"he":"גליל תחתון 56","en":"Golan 56"},"coverTime":60,"locations":[743,1138],"geometry":{"bounds":{"northeast":{"lat":32.793375,"lng":35.5627819},"southwest":{"lat":32.788537,"lng":35.495282}},"location":{"lat":32.790955999999994,"lng":35.529031950000004}}},"57":{"id":57,"region":{"he":"גליל תחתון","en":"Golan"},"name":{"he":"גליל תחתון 57","en":"Golan 57"},"coverTime":60,"locations":[249,766,858,907,1021,1092,1142,1393,1442,1578],"geometry":{"bounds":{"northeast":{"lat":32.806163,"lng":35.480318},"southwest":{"lat":32.9112069,"lng":35.3508791}},"location":{"lat":32.85868495,"lng":35.41559855}}},"60":{"id":60,"region":{"he":"גליל תחתון","en":"Golan"},"name":{"he":"גליל תחתון 60","en":"Golan 60"},"coverTime":60,"locations":[48,221,225,557,615,687,702,708,796,859,861,996,1047,1078,1318,1328,1478,1483,1541,1633,1847],"geometry":{"bounds":{"northeast":{"lat":32.0487786,"lng":35.399854},"southwest":{"lat":32.916837,"lng":34.7926889}},"location":{"lat":32.4828078,"lng":35.09627145}}},"61":{"id":61,"region":{"he":"גליל תחתון","en":"Golan"},"name":{"he":"גליל תחתון 61","en":"Golan 61"},"coverTime":60,"locations":[350,1367,1658,1661],"geometry":{"bounds":{"northeast":{"lat":32.78583,"lng":35.344536},"southwest":{"lat":32.7862291,"lng":35.29655}},"location":{"lat":32.786029549999995,"lng":35.320543}}},"63":{"id":63,"region":{"he":"גליל תחתון","en":"Golan"},"name":{"he":"גליל תחתון 63","en":"Golan 63"},"coverTime":60,"locations":[27,74,108,179,206,231,270,582,613,648,726,763,773,789,790,808,810,835,836,926,1048,1084,1139,1156,1225,1311,1359,1473,1484,1485,1486,1487,1586,1636,1704,1753,1766,1779,1791],"geometry":{"bounds":{"northeast":{"lat":32.7603601,"lng":35.286862},"southwest":{"lat":32.900956,"lng":35.1186861}},"location":{"lat":32.83065805,"lng":35.20277405}}},"70":{"id":70,"region":{"he":"הקריות","en":"Golan"},"name":{"he":"הקריות 70","en":"Golan 70"},"coverTime":60,"locations":[102,876,1609,1611,1614,1616,1622],"geometry":{"bounds":{"northeast":{"lat":32.166314,"lng":35.125125},"southwest":{"lat":32.834581,"lng":35.0562187}},"location":{"lat":32.5004475,"lng":35.09067185}}},"71":{"id":71,"region":{"he":"הקריות","en":"Golan"},"name":{"he":"הקריות 71","en":"Golan 71"},"coverTime":60,"locations":[47,98,144,211,777,891,893,908,909,1343,1608,1660,1674,1692],"geometry":{"bounds":{"northeast":{"lat":32.7476661,"lng":35.150244},"southwest":{"lat":32.833511,"lng":35.055403}},"location":{"lat":32.790588549999995,"lng":35.1028235}}},"75":{"id":75,"region":{"he":"חיפה","en":"Golan"},"name":{"he":"חיפה 75","en":"Golan 75"},"coverTime":60,"locations":[601,712,755,884],"geometry":{"bounds":{"northeast":{"lat":32.7575021,"lng":35.079493},"southwest":{"lat":32.7565638,"lng":34.952689}},"location":{"lat":32.75703295,"lng":35.016091}}},"78":{"id":78,"region":{"he":"חיפה","en":"Golan"},"name":{"he":"חיפה 78","en":"Golan 78"},"coverTime":60,"locations":[1281],"geometry":{"bounds":{"northeast":{"lat":32.82112,"lng":35.0026484},"southwest":{"lat":32.8173802,"lng":34.997906}},"location":{"lat":32.819250100000005,"lng":35.0002772}}},"80":{"id":80,"region":{"he":"כרמל","en":"Carmel"},"name":{"he":"כרמל 80","en":"Carmel 80"},"coverTime":60,"locations":[1296],"geometry":{"bounds":{"northeast":{"lat":32.788205,"lng":35.0708479},"southwest":{"lat":32.745517,"lng":35.013265}},"location":{"lat":32.766861,"lng":35.04205645}}},"81":{"id":81,"region":{"he":"כרמל","en":"Carmel"},"name":{"he":"כרמל 81","en":"Carmel 81"},"coverTime":60,"locations":[343,456,803,1022,1213,1275,1409,1418,1427,1499],"geometry":{"bounds":{"northeast":{"lat":32.6724059,"lng":35.002044},"southwest":{"lat":32.7184539,"lng":34.9262215}},"location":{"lat":32.6954299,"lng":34.96413275}}},"82":{"id":82,"region":{"he":"כרמל","en":"Carmel"},"name":{"he":"כרמל 82","en":"Carmel 82"},"coverTime":60,"locations":[280,466,537,1469],"geometry":{"bounds":{"northeast":{"lat":32.711865,"lng":35.0829939},"southwest":{"lat":32.728436,"lng":35.001446}},"location":{"lat":32.7201505,"lng":35.04221995}}},"86":{"id":86,"region":{"he":"עמק יזרעאל","en":"Carmel"},"name":{"he":"עמק יזרעאל 86","en":"Carmel 86"},"coverTime":60,"locations":[96,185,305,383,964,1613,1785],"geometry":{"bounds":{"northeast":{"lat":32.0561905,"lng":35.1636689},"southwest":{"lat":32.729966,"lng":34.8527264}},"location":{"lat":32.39307825,"lng":35.00819765}}},"87":{"id":87,"region":{"he":"עמק יזרעאל","en":"Carmel"},"name":{"he":"עמק יזרעאל 87","en":"Carmel 87"},"coverTime":60,"locations":[182,322,354,462,485,501,816,867,914,1024,1091,1196,1215,1396,1488,1687,1693,1724,1776,1796,1833],"geometry":{"bounds":{"northeast":{"lat":32.6672909,"lng":35.274132},"southwest":{"lat":32.739492,"lng":35.1357289}},"location":{"lat":32.70339145,"lng":35.20493045}}},"89":{"id":89,"region":{"he":"עמק יזרעאל","en":"Carmel"},"name":{"he":"עמק יזרעאל 89","en":"Carmel 89"},"coverTime":60,"locations":[602,881],"geometry":{"bounds":{"northeast":{"lat":32.6184829,"lng":35.219083},"southwest":{"lat":32.641504,"lng":35.1826041}},"location":{"lat":32.62999345,"lng":35.20084355}}},"90":{"id":90,"region":{"he":"עמק יזרעאל","en":"Carmel"},"name":{"he":"עמק יזרעאל 90","en":"Carmel 90"},"coverTime":60,"locations":[106,542,555,764,1129,1154,1155,1188,1230,1255,1313,1420,1421,1470],"geometry":{"bounds":{"northeast":{"lat":32.5448769,"lng":35.4086561},"southwest":{"lat":32.644817,"lng":35.247241}},"location":{"lat":32.594846950000004,"lng":35.32794855}}},"93":{"id":93,"region":{"he":"עמק יזרעאל","en":"Carmel"},"name":{"he":"עמק יזרעאל 93","en":"Carmel 93"},"coverTime":60,"locations":[53,65,84,399,454,487,488,515,539,678,750,795,811,916,1031,1046,1064,1079,1269,1533,1560,1675,1695,1816],"geometry":{"bounds":{"northeast":{"lat":32.517861,"lng":35.450784},"southwest":{"lat":32.5974351,"lng":35.2306201}},"location":{"lat":32.55764805,"lng":35.340702050000004}}},"95":{"id":95,"region":{"he":"תבור","en":"Golan"},"name":{"he":"תבור 95","en":"Golan 95"},"coverTime":60,"locations":[131,364,598,606,814,883,890,919,1052,1166,1294,1295,1428,1489,1558,1671,1819],"geometry":{"bounds":{"northeast":{"lat":32.633555,"lng":35.41234499999999},"southwest":{"lat":32.753182,"lng":35.2321939}},"location":{"lat":32.693368500000005,"lng":35.32226944999999}}},"96":{"id":96,"region":{"he":"תבור","en":"Golan"},"name":{"he":"תבור 96","en":"Golan 96"},"coverTime":60,"locations":[121,346,493,540,748,838,924,950,962,1407,1713,1738,1780],"geometry":{"bounds":{"northeast":{"lat":32.625577,"lng":35.4584709},"southwest":{"lat":32.748636,"lng":35.324885}},"location":{"lat":32.6871065,"lng":35.39167795}}},"98":{"id":98,"region":{"he":"תבור","en":"Golan"},"name":{"he":"תבור 98","en":"Golan 98"},"coverTime":60,"locations":[72,177,210,223,224,307,320,461,543,544,595,600,774,851,852,918,930,986,1087,1508,1509,1510,1717,1794],"geometry":{"bounds":{"northeast":{"lat":32.0520896,"lng":35.588392},"southwest":{"lat":32.7831351,"lng":34.8577183}},"location":{"lat":32.41761235,"lng":35.22305515}}},"102":{"id":102,"region":{"he":"מנשה","en":"Menashe"},"name":{"he":"מנשה 102","en":"Menashe 102"},"coverTime":90,"locations":[408,551,590,639,971,1004,1109,1159,1246,1371,1400,1511,1564],"geometry":{"bounds":{"northeast":{"lat":32.570854,"lng":35.010743},"southwest":{"lat":32.643257,"lng":34.9141233}},"location":{"lat":32.6070555,"lng":34.962433149999995}}},"103":{"id":103,"region":{"he":"מנשה","en":"Menashe"},"name":{"he":"מנשה 103","en":"Menashe 103"},"coverTime":90,"locations":[190,424,508,580,599,792,793,1028,1034,1174,1413,1414,1682,1689],"geometry":{"bounds":{"northeast":{"lat":32.5608891,"lng":35.18428},"southwest":{"lat":32.6450099,"lng":35.049648}},"location":{"lat":32.602949499999994,"lng":35.116963999999996}}},"104":{"id":104,"region":{"he":"מנשה","en":"Menashe"},"name":{"he":"מנשה 104","en":"Menashe 104"},"coverTime":90,"locations":[49,184,313,381,444,476,885,1104,1457,1649],"geometry":{"bounds":{"northeast":{"lat":32.5087229,"lng":35.0493959},"southwest":{"lat":32.5569711,"lng":34.9007066}},"location":{"lat":32.532847000000004,"lng":34.97505125}}},"105":{"id":105,"region":{"he":"מנשה","en":"Menashe"},"name":{"he":"מנשה 105","en":"Menashe 105"},"coverTime":90,"locations":[90,1590,1732],"geometry":{"bounds":{"northeast":{"lat":32.4976997,"lng":34.953774},"southwest":{"lat":32.487757,"lng":34.8862131}},"location":{"lat":32.49272835,"lng":34.91999355}}},"106":{"id":106,"region":{"he":"מנשה","en":"Menashe"},"name":{"he":"מנשה 106","en":"Menashe 106"},"coverTime":90,"locations":[511,946,1177,1202,1432,1438,1529],"geometry":{"bounds":{"northeast":{"lat":31.799629,"lng":35.0149209},"southwest":{"lat":32.4847581,"lng":34.8176983}},"location":{"lat":32.14219355,"lng":34.916309600000005}}},"107":{"id":107,"region":{"he":"מנשה","en":"Menashe"},"name":{"he":"מנשה 107","en":"Menashe 107"},"coverTime":90,"locations":[686],"geometry":{"bounds":{"northeast":{"lat":32.4781559,"lng":34.9783341},"southwest":{"lat":32.403124,"lng":34.8693936}},"location":{"lat":32.44063995,"lng":34.923863850000004}}},"108":{"id":108,"region":{"he":"מנשה","en":"Menashe"},"name":{"he":"מנשה 108","en":"Menashe 108"},"coverTime":90,"locations":[469,518,1003,1124,1725,1786,1825],"geometry":{"bounds":{"northeast":{"lat":32.41118,"lng":35.033094},"southwest":{"lat":32.452321,"lng":34.9435369}},"location":{"lat":32.4317505,"lng":34.98831545}}},"112":{"id":112,"region":{"he":"עירון","en":"Menashe"},"name":{"he":"עירון 112","en":"Menashe 112"},"coverTime":90,"locations":[78,153,163,400,535,538,657,952,1088,1140,1494,1601,1670],"geometry":{"bounds":{"northeast":{"lat":32.46283,"lng":35.138023},"southwest":{"lat":32.496459,"lng":35.0227609}},"location":{"lat":32.4796445,"lng":35.08039195}}},"113":{"id":113,"region":{"he":"עירון","en":"Menashe"},"name":{"he":"עירון 113","en":"Menashe 113"},"coverTime":90,"locations":[77,382,478,662,1062,1119],"geometry":{"bounds":{"northeast":{"lat":32.5070429,"lng":35.2092261},"southwest":{"lat":32.550657,"lng":35.079392}},"location":{"lat":32.52884995,"lng":35.144309050000004}}},"118":{"id":118,"region":{"he":"שומרון","en":"Shomron"},"name":{"he":"שומרון 118","en":"Shomron 118"},"coverTime":90,"locations":[75,79,258,589,629,633,650,651,711,740,747,767,809,847,887,949,1006,1090,1231,1235,1322,1349,1479,1496,1515,1599,1659,1792,1809,1839],"geometry":{"bounds":{"northeast":{"lat":32.423491,"lng":35.185003},"southwest":{"lat":32.4773461,"lng":35.1139791}},"location":{"lat":32.450418549999995,"lng":35.14949105}}},"119":{"id":119,"region":{"he":"שומרון","en":"Shomron"},"name":{"he":"שומרון 119","en":"Shomron 119"},"coverTime":90,"locations":[18,76,113,117,127,135,151,152,213,233,257,259,279,344,363,413,419,435,438,439,443,446,561,566,573,584,616,625,626,658,659,745,746,759,762,771,846,869,953,955,983,1038,1070,1072,1096,1180,1228,1232,1233,1234,1256,1306,1319,1321,1326,1327,1346,1355,1388,1395,1402,1464,1465,1466,1475,1476,1481,1490,1498,1513,1519,1526,1567,1628,1677,1745,1807,1831,1835],"geometry":{"bounds":{"northeast":{"lat":32.948267,"lng":35.1634931},"southwest":{"lat":32.9143631,"lng":35.1209491}},"location":{"lat":32.93131505,"lng":35.1422211}}},"120":{"id":120,"region":{"he":"שומרון","en":"Shomron"},"name":{"he":"שומרון 120","en":"Shomron 120"},"coverTime":90,"locations":[16,61,69,123,128,167,180,232,255,275,281,295,304,323,342,356,362,396,423,430,434,441,477,565,578,610,632,636,649,663,680,689,769,818,848,882,902,937,941,948,951,1019,1033,1189,1305,1309,1329,1338,1341,1364,1370,1375,1383,1422,1441,1445,1463,1467,1468,1477,1516,1536,1537,1571,1582,1584,1632,1651,1703,1712,1749,1765,1811],"geometry":{"bounds":{"northeast":{"lat":31.458608,"lng":35.374511},"southwest":{"lat":32.281391,"lng":34.535496}},"location":{"lat":31.8699995,"lng":34.955003500000004}}},"121":{"id":121,"region":{"he":"שומרון","en":"Shomron"},"name":{"he":"שומרון 121","en":"Shomron 121"},"coverTime":90,"locations":[20,32,150,197,199,264,288,432,564,653,655,665,667,668,821,920,961,1094,1122,1224,1333,1342,1381,1382,1459,1472,1546,1597,1604,1625,1787],"geometry":{"bounds":{"northeast":{"lat":32.1206711,"lng":35.159583},"southwest":{"lat":32.1942189,"lng":34.97519}},"location":{"lat":32.157445,"lng":35.0673865}}},"122":{"id":122,"region":{"he":"שומרון","en":"Shomron"},"name":{"he":"שומרון 122","en":"Shomron 122"},"coverTime":90,"locations":[218,401,675,855,1151,1330,1403,1534,1591,1618,1644],"geometry":{"bounds":{"northeast":{"lat":32.111852,"lng":35.2376899},"southwest":{"lat":32.115963,"lng":35.10181499999999}},"location":{"lat":32.113907499999996,"lng":35.16975244999999}}},"123":{"id":123,"region":{"he":"שומרון","en":"Shomron"},"name":{"he":"שומרון 123","en":"Shomron 123"},"coverTime":90,"locations":[10,289,392,567,624,1372,1449,1504,1639,1699],"geometry":{"bounds":{"northeast":{"lat":32.0540919,"lng":35.0683311},"southwest":{"lat":32.0693119,"lng":35.0331251}},"location":{"lat":32.0617019,"lng":35.0507281}}},"124":{"id":124,"region":{"he":"שומרון","en":"Shomron"},"name":{"he":"שומרון 124","en":"Shomron 124"},"coverTime":90,"locations":[81,125,218,253,254,349,429,431,560,562,571,574,666,715,770,839,868,943,963,992,1049,1117,1191,1304,1324,1347,1353,1356,1389,1390,1453,1493,1603],"geometry":{"bounds":{"northeast":{"lat":32.0078759,"lng":35.253438},"southwest":{"lat":32.1146471,"lng":35.112572}},"location":{"lat":32.0612615,"lng":35.183005}}},"125":{"id":125,"region":{"he":"שומרון","en":"Shomron"},"name":{"he":"שומרון 125","en":"Shomron 125"},"coverTime":90,"locations":[103,411,426,568,569,654,751,834,921,1027,1039,1054,1320,1448,1471,1570,1585,1605,1668,1678,1709,1763,1805,1832],"geometry":{"bounds":{"northeast":{"lat":31.9599541,"lng":35.344506},"southwest":{"lat":32.0873091,"lng":35.249675}},"location":{"lat":32.0236316,"lng":35.2970905}}},"126":{"id":126,"region":{"he":"שומרון","en":"Shomron"},"name":{"he":"שומרון 126","en":"Shomron 126"},"coverTime":90,"locations":[15,41,45,133,256,266,272,284,285,297,308,324,331,333,334,357,358,359,412,414,437,440,445,463,548,553,563,575,576,652,656,669,753,761,776,844,934,945,1055,1242,1254,1288,1316,1337,1399,1423,1431,1433,1435,1522,1588,1594,1634,1637,1676,1714,1750],"geometry":{"bounds":{"northeast":{"lat":31.8814839,"lng":35.748393},"southwest":{"lat":33.225705,"lng":34.8061136}},"location":{"lat":32.55359445,"lng":35.2772533}}},"127":{"id":127,"region":{"he":"שומרון","en":"Shomron"},"name":{"he":"שומרון 127","en":"Shomron 127"},"coverTime":90,"locations":[282,420,428,458,467,1192],"geometry":{"bounds":{"northeast":{"lat":31.8520879,"lng":35.190793},"southwest":{"lat":31.842089,"lng":35.1374421}},"location":{"lat":31.84708845,"lng":35.16411755}}},"128":{"id":128,"region":{"he":"בקעת בית שאן","en":"Carmel"},"name":{"he":"בקעת בית שאן 128","en":"Carmel 128"},"coverTime":60,"locations":[100,107,265,287,303,317,351,531,690,692,695,719,730,756,823,956,1041,1068,1082,1095,1105,1114,1131,1203,1206,1267,1412,1655,1666,1706,1718,1727,1736,1769,1822],"geometry":{"bounds":{"northeast":{"lat":32.424924,"lng":35.569492},"southwest":{"lat":32.61611,"lng":35.4111249}},"location":{"lat":32.520517,"lng":35.49030845}}},"130":{"id":130,"region":{"he":"בקעה","en":"Bik'a"},"name":{"he":"בקעה 130","en":"Bik'a 130"},"coverTime":90,"locations":[215,387,391,630,670,720,722,1056,1074,1149,1169,1348,1502,1532,1662,1664,1739,1812,1814],"geometry":{"bounds":{"northeast":{"lat":32.167615,"lng":35.5356491},"southwest":{"lat":32.36260300000001,"lng":35.419948}},"location":{"lat":32.265109,"lng":35.47779855}}},"131":{"id":131,"region":{"he":"בקעה","en":"Bik'a"},"name":{"he":"בקעה 131","en":"Bik'a 131"},"coverTime":90,"locations":[504,815,1167,1772],"geometry":{"bounds":{"northeast":{"lat":32.067042,"lng":35.495149},"southwest":{"lat":32.1066611,"lng":35.4704539}},"location":{"lat":32.08685155,"lng":35.48280145}}},"132":{"id":132,"region":{"he":"בקעה","en":"Bik'a"},"name":{"he":"בקעה 132","en":"Bik'a 132"},"coverTime":90,"locations":[506,549,800,1042,1113,1280,1289,1297,1362,1429,1521,1525,1803],"geometry":{"bounds":{"northeast":{"lat":31.9110939,"lng":35.4718809},"southwest":{"lat":32.0589439,"lng":35.380485}},"location":{"lat":31.9850189,"lng":35.42618295}}},"133":{"id":133,"region":{"he":"בקעה","en":"Bik'a"},"name":{"he":"בקעה 133","en":"Bik'a 133"},"coverTime":90,"locations":[178,194,302,455,621,827,842,871,1011,1118,1141,1220,1221,1237,1398,1451,1474,1593,1672],"geometry":{"bounds":{"northeast":{"lat":31.7554499,"lng":35.5009569},"southwest":{"lat":31.8456181,"lng":35.2661211}},"location":{"lat":31.800534,"lng":35.383539}}},"137":{"id":137,"region":{"he":"עמק חפר","en":"Hefer Valley"},"name":{"he":"עמק חפר 137","en":"Hefer Valley 137"},"coverTime":90,"locations":[187,191,309,314,318,449,470,471,683,703,709,736,896,898,1010,1077,1287,1410],"geometry":{"bounds":{"northeast":{"lat":32.3846981,"lng":34.9441921},"southwest":{"lat":32.4030479,"lng":34.8606771}},"location":{"lat":32.393873,"lng":34.9024346}}},"138":{"id":138,"region":{"he":"שרון","en":"Sharon"},"name":{"he":"שרון 138","en":"Sharon 138"},"coverTime":90,"locations":[52,319,360,404,481,520,592,677,906,913,1101,1176,1229,1302,1549,1754],"geometry":{"bounds":{"northeast":{"lat":32.321084,"lng":34.9074709},"southwest":{"lat":32.3618779,"lng":34.8285249}},"location":{"lat":32.341480950000005,"lng":34.8679979}}},"139":{"id":139,"region":{"he":"עמק חפר","en":"Hefer Valley"},"name":{"he":"עמק חפר 139","en":"Hefer Valley 139"},"coverTime":90,"locations":[115,120,290,372,450,738,749,752,812,843,895,917,940,1178,1264,1385,1416,1439,1512,1530,1552,1553,1554,1555,1572,1595,1688,1722,1783,1818],"geometry":{"bounds":{"northeast":{"lat":32.2011559,"lng":35.030478},"southwest":{"lat":32.301751,"lng":34.883384}},"location":{"lat":32.25145345,"lng":34.956931}}},"140":{"id":140,"region":{"he":"שרון","en":"Sharon"},"name":{"he":"שרון 140","en":"Sharon 140"},"coverTime":90,"locations":[468,1701,1705],"geometry":{"bounds":{"northeast":{"lat":32.173736,"lng":34.891356},"southwest":{"lat":32.192307,"lng":34.8180749}},"location":{"lat":32.183021499999995,"lng":34.85471545}}},"141":{"id":141,"region":{"he":"שרון","en":"Sharon"},"name":{"he":"שרון 141","en":"Sharon 141"},"coverTime":90,"locations":[512,936,1214,1547],"geometry":{"bounds":{"northeast":{"lat":32.177866,"lng":34.9569},"southwest":{"lat":32.190877,"lng":34.8864479}},"location":{"lat":32.1843715,"lng":34.92167395}}},"142":{"id":142,"region":{"he":"שרון","en":"Sharon"},"name":{"he":"שרון 142","en":"Sharon 142"},"coverTime":90,"locations":[56,68,219,316,378,384,526,623,737,820,933,1621,1788,1817],"geometry":{"bounds":{"northeast":{"lat":32.0550083,"lng":34.8966211},"southwest":{"lat":32.264979,"lng":34.759367}},"location":{"lat":32.15999365,"lng":34.82799405}}},"143":{"id":143,"region":{"he":"שרון","en":"Sharon"},"name":{"he":"שרון 143","en":"Sharon 143"},"coverTime":90,"locations":[97,192,436,524,593,676,681,707,826,829,880,925,947,1181,1216,1279,1360,1680,1735],"geometry":{"bounds":{"northeast":{"lat":32.13171,"lng":35.008175},"southwest":{"lat":32.162816,"lng":34.855284}},"location":{"lat":32.147262999999995,"lng":34.9317295}}},"149":{"id":149,"region":{"he":"עמק חפר","en":"Hefer Valley"},"name":{"he":"עמק חפר 149","en":"Hefer Valley 149"},"coverTime":90,"locations":[85,109,234,235,260,448,605,637,641,990,1029,1065,1145,1236],"geometry":{"bounds":{"northeast":{"lat":32.355374,"lng":35.281907},"southwest":{"lat":32.9621179,"lng":34.978156}},"location":{"lat":32.65874595,"lng":35.1300315}}},"150":{"id":150,"region":{"he":"עמק חפר","en":"Hefer Valley"},"name":{"he":"עמק חפר 150","en":"Hefer Valley 150"},"coverTime":90,"locations":[243,252,299,405,513,607,724,781,804,915,922,1262,1368,1834],"geometry":{"bounds":{"northeast":{"lat":32.3116969,"lng":35.017213},"southwest":{"lat":32.3576149,"lng":34.9037141}},"location":{"lat":32.3346559,"lng":34.96046355}}},"155":{"id":155,"region":{"he":"דן","en":"Dan"},"name":{"he":"דן 155","en":"Dan 155"},"coverTime":90,"locations":[507,604,614,960,1690],"geometry":{"bounds":{"northeast":{"lat":32.158889,"lng":34.86803},"southwest":{"lat":32.1774249,"lng":34.7913391}},"location":{"lat":32.16815695,"lng":34.829684549999996}}},"157":{"id":157,"region":{"he":"דן","en":"Dan"},"name":{"he":"דן 157","en":"Dan 157"},"coverTime":90,"locations":[1813],"geometry":{"bounds":{"northeast":{"lat":32.1465074,"lng":34.8519761},"southwest":{"lat":32.0292531,"lng":34.7425159}},"location":{"lat":32.08788025,"lng":34.797246}}},"160":{"id":160,"region":{"he":"דן","en":"Dan"},"name":{"he":"דן 160","en":"Dan 160"},"coverTime":90,"locations":[369,479,483,694,1686],"geometry":{"bounds":{"northeast":{"lat":32.082305,"lng":34.86011209999999},"southwest":{"lat":32.0689919,"lng":34.797914}},"location":{"lat":32.07564845,"lng":34.82901304999999}}},"161":{"id":161,"region":{"he":"דן","en":"Dan"},"name":{"he":"דן 161","en":"Dan 161"},"coverTime":90,"locations":[89,525,786,873,1126,1207,1308,1606,1685],"geometry":{"bounds":{"northeast":{"lat":32.039807,"lng":34.9078431},"southwest":{"lat":32.0935735,"lng":34.8369391}},"location":{"lat":32.06669025,"lng":34.8723911}}},"162":{"id":162,"region":{"he":"דן","en":"Dan"},"name":{"he":"דן 162","en":"Dan 162"},"coverTime":90,"locations":[99,406,697,1146],"geometry":{"bounds":{"northeast":{"lat":32.033458,"lng":34.8217581},"southwest":{"lat":32.0094579,"lng":34.733055}},"location":{"lat":32.02145795,"lng":34.777406549999995}}},"168":{"id":168,"region":{"he":"שפלה","en":"Shfela"},"name":{"he":"שפלה 168","en":"Shfela 168"},"coverTime":90,"locations":[465,534,939,1538,1838],"geometry":{"bounds":{"northeast":{"lat":32.07104,"lng":34.932325},"southwest":{"lat":32.0946811,"lng":34.845652}},"location":{"lat":32.08286055000001,"lng":34.888988499999996}}},"169":{"id":169,"region":{"he":"שפלה","en":"Shfela"},"name":{"he":"שפלה 169","en":"Shfela 169"},"coverTime":90,"locations":[195,242,376,475,1032,1050,1226,1243,1248,1673],"geometry":{"bounds":{"northeast":{"lat":32.030075,"lng":34.9690681},"southwest":{"lat":32.057877,"lng":34.883817}},"location":{"lat":32.043976,"lng":34.926442550000004}}},"170":{"id":170,"region":{"he":"שפלה","en":"Shfela"},"name":{"he":"שפלה 170","en":"Shfela 170"},"coverTime":90,"locations":[1443,1640],"geometry":{"bounds":{"northeast":{"lat":32.088196,"lng":34.9994091},"southwest":{"lat":32.0712249,"lng":34.932534}},"location":{"lat":32.07971045,"lng":34.96597155}}},"171":{"id":171,"region":{"he":"שפלה","en":"Shfela"},"name":{"he":"שפלה 171","en":"Shfela 171"},"coverTime":90,"locations":[1057],"geometry":{"bounds":{"northeast":{},"southwest":{}},"location":{"lat":null,"lng":null}}},"172":{"id":172,"region":{"he":"שפלה","en":"Shfela"},"name":{"he":"שפלה 172","en":"Shfela 172"},"coverTime":90,"locations":[1282],"geometry":{"bounds":{"northeast":{},"southwest":{}},"location":{"lat":null,"lng":null}}},"173":{"id":173,"region":{"he":"שפלה","en":"Shfela"},"name":{"he":"שפלה 173","en":"Shfela 173"},"coverTime":90,"locations":[327,340,402,685,754,1161,1744],"geometry":{"bounds":{"northeast":{"lat":31.972253,"lng":34.967918},"southwest":{"lat":32.008644,"lng":34.920676}},"location":{"lat":31.9904485,"lng":34.944297}}},"174":{"id":174,"region":{"he":"שפלה","en":"Shfela"},"name":{"he":"שפלה 174","en":"Shfela 174"},"coverTime":90,"locations":[111,296,519,638,718,778,904,911,1175,1561],"geometry":{"bounds":{"northeast":{"lat":31.981378,"lng":34.9341589},"southwest":{"lat":32.012312,"lng":34.81671499999999}},"location":{"lat":31.996845,"lng":34.875436949999994}}},"175":{"id":175,"region":{"he":"שפלה","en":"Shfela"},"name":{"he":"שפלה 175","en":"Shfela 175"},"coverTime":90,"locations":[516,1252,1518,1643],"geometry":{"bounds":{"northeast":{"lat":31.936216,"lng":34.8432789},"southwest":{"lat":31.940499,"lng":34.702285}},"location":{"lat":31.938357500000002,"lng":34.77278195}}},"178":{"id":178,"region":{"he":"שפלה","en":"Shfela"},"name":{"he":"שפלה 178","en":"Shfela 178"},"coverTime":90,"locations":[239,832,1137,1565,1684],"geometry":{"bounds":{"northeast":{"lat":31.914685,"lng":34.8997901},"southwest":{"lat":31.926392,"lng":34.8178749}},"location":{"lat":31.9205385,"lng":34.8588325}}},"179":{"id":179,"region":{"he":"שפלה","en":"Shfela"},"name":{"he":"שפלה 179","en":"Shfela 179"},"coverTime":90,"locations":[110,367,368,502,969,993,1277],"geometry":{"bounds":{"northeast":{"lat":31.945762,"lng":34.93534},"southwest":{"lat":31.9572249,"lng":34.85316090000001}},"location":{"lat":31.95149345,"lng":34.89425045}}},"181":{"id":181,"region":{"he":"שפלה","en":"Shfela"},"name":{"he":"שפלה 181","en":"Shfela 181"},"coverTime":90,"locations":[246,509,742,888,889,957,1000,1007,1009,1036,1037,1063,1183,1223,1257,1764,1782],"geometry":{"bounds":{"northeast":{"lat":31.852941,"lng":35.0638319},"southwest":{"lat":31.9322721,"lng":34.92828}},"location":{"lat":31.89260655,"lng":34.99605595}}},"182":{"id":182,"region":{"he":"שפלה","en":"Shfela"},"name":{"he":"שפלה 182","en":"Shfela 182"},"coverTime":90,"locations":[126,464,496,517,1286,1293,1667],"geometry":{"bounds":{"northeast":{"lat":31.8735271,"lng":34.8507189},"southwest":{"lat":31.914654,"lng":34.757786}},"location":{"lat":31.89409055,"lng":34.80425245}}},"183":{"id":183,"region":{"he":"שפלה","en":"Shfela"},"name":{"he":"שפלה 183","en":"Shfela 183"},"coverTime":90,"locations":[312,335,1286,1394],"geometry":{"bounds":{"northeast":{"lat":31.923519,"lng":34.821876},"southwest":{"lat":31.92714,"lng":34.757786}},"location":{"lat":31.9253295,"lng":34.78983100000001}}},"184":{"id":184,"region":{"he":"שפלה","en":"Shfela"},"name":{"he":"שפלה 184","en":"Shfela 184"},"coverTime":90,"locations":[315,336,494,521,523,696,784,807,819,877,879,959,974,1051,1160,1170,1171,1290,1292,1344,1386,1506,1539,1620,1681],"geometry":{"bounds":{"northeast":{"lat":31.818975,"lng":34.95477700000001},"southwest":{"lat":31.893912,"lng":34.807074}},"location":{"lat":31.856443499999997,"lng":34.880925500000004}}},"188":{"id":188,"region":{"he":"יהודה","en":"Yehuda"},"name":{"he":"יהודה 188","en":"Yehuda 188"},"coverTime":90,"locations":[2,54,67,82,170,230,277,291,353,386,460,480,497,558,612,643,671,758,831,872,1059,1086,1097,1199,1218,1219,1244,1247,1298,1503,1559,1566,1653,1823,1836,1848,1849],"geometry":{"bounds":{"northeast":{"lat":31.570277,"lng":35.0348731},"southwest":{"lat":31.827414,"lng":34.888964}},"location":{"lat":31.6988455,"lng":34.96191855}}},"189":{"id":189,"region":{"he":"בית שמש","en":"Beit Shemesh"},"name":{"he":"בית שמש 189","en":"Beit Shemesh 189"},"coverTime":90,"locations":[26,130,325,388,473,780,785,865,1061,1205,1253,1284,1430,1437,1615,1696,1741,1752],"geometry":{"bounds":{"northeast":{"lat":31.7227319,"lng":35.125865},"southwest":{"lat":31.828807,"lng":35.029178}},"location":{"lat":31.77576945,"lng":35.0775215}}},"190":{"id":190,"region":{"he":"בית שמש","en":"Beit Shemesh"},"name":{"he":"בית שמש 190","en":"Beit Shemesh 190"},"coverTime":90,"locations":[263,306,329,330,608,1016,1045,1116,1543,1619],"geometry":{"bounds":{"northeast":{"lat":31.7866089,"lng":35.180508},"southwest":{"lat":31.82024909999999,"lng":35.1022219}},"location":{"lat":31.803428999999994,"lng":35.14136495}}},"191":{"id":191,"region":{"he":"בית שמש","en":"Beit Shemesh"},"name":{"he":"בית שמש 191","en":"Beit Shemesh 191"},"coverTime":90,"locations":[58,91,1005,1454,1551],"geometry":{"bounds":{"northeast":{"lat":31.7223819,"lng":35.1605759},"southwest":{"lat":31.7570329,"lng":35.084035}},"location":{"lat":31.7397074,"lng":35.12230545}}},"194":{"id":194,"region":{"he":"ירושלים","en":"Jerusalem"},"name":{"he":"ירושלים 194","en":"Jerusalem 194"},"coverTime":90,"locations":[7,28,141,273,283,311,570,710,825,1462,1697],"geometry":{"bounds":{"northeast":{"lat":31.747036,"lng":35.2652869},"southwest":{"lat":31.7336611,"lng":35.0854311}},"location":{"lat":31.74034855,"lng":35.175359}}},"200":{"id":200,"region":{"he":"יהודה","en":"Yehuda"},"name":{"he":"יהודה 200","en":"Yehuda 200"},"coverTime":90,"locations":[1,31,73,80,83,143,205,217,245,247,262,348,355,390,417,418,421,427,536,545,617,644,672,688,739,875,1066,1112,1120,1125,1132,1148,1227,1350,1361,1392,1397,1482,1576,1635,1702,1804,1837,1843],"geometry":{"bounds":{"northeast":{"lat":31.5927021,"lng":35.391822},"southwest":{"lat":31.7461981,"lng":35.1827919}},"location":{"lat":31.6694501,"lng":35.28730695}}},"206":{"id":206,"region":{"he":"יהודה","en":"Yehuda"},"name":{"he":"יהודה 206","en":"Yehuda 206"},"coverTime":90,"locations":[19,162,181,196,212,278,321,332,341,361,407,409,410,415,609,618,664,700,714,727,840,944,975,1025,1043,1147,1208,1238,1317,1325,1350,1642],"geometry":{"bounds":{"northeast":{"lat":31.612684,"lng":35.30292},"southwest":{"lat":32.9937749,"lng":35.0938}},"location":{"lat":32.30322945,"lng":35.19836}}},"207":{"id":207,"region":{"he":"יהודה","en":"Yehuda"},"name":{"he":"יהודה 207","en":"Yehuda 207"},"coverTime":90,"locations":[3,8,9,17,64,124,139,145,149,155,160,166,168,208,338,339,374,447,546,550,552,572,577,611,619,634,660,661,673,674,679,682,765,798,802,866,965,979,982,984,1017,1106,1111,1133,1134,1194,1210,1312,1314,1323,1331,1351,1363,1366,1404,1406,1461,1500,1507,1520,1581,1589,1607,1629,1638,1652,1663,1746,1761,1774,1777,1840,1846],"geometry":{"bounds":{"northeast":{"lat":31.155575,"lng":35.390132},"southwest":{"lat":32.8924931,"lng":34.953407}},"location":{"lat":32.02403405,"lng":35.171769499999996}}},"210":{"id":210,"region":{"he":"ים המלח","en":"Yehuda"},"name":{"he":"ים המלח 210","en":"Yehuda 210"},"coverTime":90,"locations":[62,1136,1144],"geometry":{"bounds":{"northeast":{"lat":31.5713,"lng":35.439083},"southwest":{"lat":31.676556,"lng":35.3985139}},"location":{"lat":31.623928,"lng":35.41879845}}},"217":{"id":217,"region":{"he":"עוטף עזה","en":"Gaza Perimeter"},"name":{"he":"עוטף עזה 217","en":"Gaza Perimeter 217"},"coverTime":15,"locations":[635,978],"geometry":{"bounds":{"northeast":{"lat":31.6090319,"lng":34.5454691},"southwest":{"lat":31.60460089999999,"lng":34.5162579}},"location":{"lat":31.606816399999996,"lng":34.530863499999995}}},"218":{"id":218,"region":{"he":"עוטף עזה","en":"Gaza Perimeter"},"name":{"he":"עוטף עזה 218","en":"Gaza Perimeter 218"},"coverTime":15,"locations":[782,1299],"geometry":{"bounds":{"northeast":{"lat":31.5783799,"lng":34.5640489},"southwest":{"lat":31.582684,"lng":34.530867}},"location":{"lat":31.58053195,"lng":34.54745795}}},"219":{"id":219,"region":{"he":"עוטף עזה","en":"Gaza Perimeter"},"name":{"he":"עוטף עזה 219","en":"Gaza Perimeter 219"},"coverTime":15,"locations":[88,216],"geometry":{"bounds":{"northeast":{"lat":31.5609381,"lng":34.6070921},"southwest":{"lat":31.555049,"lng":34.56067609999999}},"location":{"lat":31.55799355,"lng":34.58388409999999}}},"220":{"id":220,"region":{"he":"עוטף עזה","en":"Gaza Perimeter"},"name":{"he":"עוטף עזה 220","en":"Gaza Perimeter 220"},"coverTime":15,"locations":[112,453,1076,1274,1740],"geometry":{"bounds":{"northeast":{"lat":31.510597,"lng":34.615238},"southwest":{"lat":31.5165291,"lng":34.568831}},"location":{"lat":31.513563050000002,"lng":34.5920345}}},"221":{"id":221,"region":{"he":"עוטף עזה","en":"Gaza Perimeter"},"name":{"he":"עוטף עזה 221","en":"Gaza Perimeter 221"},"coverTime":15,"locations":[1127],"geometry":{"bounds":{"northeast":{"lat":31.5054171,"lng":34.5719529},"southwest":{"lat":31.497633,"lng":34.556124}},"location":{"lat":31.501525049999998,"lng":34.56403845}}},"222":{"id":222,"region":{"he":"עוטף עזה","en":"Gaza Perimeter"},"name":{"he":"עוטף עזה 222","en":"Gaza Perimeter 222"},"coverTime":15,"locations":[801],"geometry":{"bounds":{"northeast":{"lat":31.4885411,"lng":34.6105971},"southwest":{"lat":31.476922,"lng":34.591798}},"location":{"lat":31.482731549999997,"lng":34.601197549999995}}},"223":{"id":223,"region":{"he":"עוטף עזה","en":"Gaza Perimeter"},"name":{"he":"עוטף עזה 223","en":"Gaza Perimeter 223"},"coverTime":15,"locations":[942,1335],"geometry":{"bounds":{"northeast":{"lat":31.475341,"lng":34.541784},"southwest":{"lat":31.47859099999999,"lng":34.525892}},"location":{"lat":31.476965999999997,"lng":34.533838}}},"224":{"id":224,"region":{"he":"עוטף עזה","en":"Gaza Perimeter"},"name":{"he":"עוטף עזה 224","en":"Gaza Perimeter 224"},"coverTime":15,"locations":[1240,1447],"geometry":{"bounds":{"northeast":{"lat":31.4573049,"lng":34.519246},"southwest":{"lat":31.467064,"lng":34.4927491}},"location":{"lat":31.462184450000002,"lng":34.505997550000004}}},"225":{"id":225,"region":{"he":"עוטף עזה","en":"Gaza Perimeter"},"name":{"he":"עוטף עזה 225","en":"Gaza Perimeter 225"},"coverTime":15,"locations":[642,691,923,1742,1751,1806,1842],"geometry":{"bounds":{"northeast":{"lat":31.426026,"lng":34.5896549},"southwest":{"lat":31.4453239,"lng":34.5182089}},"location":{"lat":31.43567495,"lng":34.553931899999995}}},"227":{"id":227,"region":{"he":"עוטף עזה","en":"Gaza Perimeter"},"name":{"he":"עוטף עזה 227","en":"Gaza Perimeter 227"},"coverTime":15,"locations":[244],"geometry":{"bounds":{"northeast":{"lat":31.427701,"lng":34.496328},"southwest":{"lat":31.4195769,"lng":34.485585}},"location":{"lat":31.423638949999997,"lng":34.490956499999996}}},"228":{"id":228,"region":{"he":"עוטף עזה","en":"Gaza Perimeter"},"name":{"he":"עוטף עזה 228","en":"Gaza Perimeter 228"},"coverTime":15,"locations":[1700],"geometry":{"bounds":{"northeast":{"lat":31.389504,"lng":34.4659949},"southwest":{"lat":31.380937,"lng":34.454523}},"location":{"lat":31.3852205,"lng":34.46025895}}},"230":{"id":230,"region":{"he":"עוטף עזה","en":"Gaza Perimeter"},"name":{"he":"עוטף עזה 230","en":"Gaza Perimeter 230"},"coverTime":15,"locations":[853],"geometry":{"bounds":{"northeast":{"lat":31.379061,"lng":34.403307},"southwest":{"lat":31.370546,"lng":34.3941899}},"location":{"lat":31.3748035,"lng":34.39874845}}},"231":{"id":231,"region":{"he":"עוטף עזה","en":"Gaza Perimeter"},"name":{"he":"עוטף עזה 231","en":"Gaza Perimeter 231"},"coverTime":15,"locations":[1278,1415],"geometry":{"bounds":{"northeast":{"lat":31.339916,"lng":34.40851},"southwest":{"lat":31.346425,"lng":34.389533}},"location":{"lat":31.3431705,"lng":34.3990215}}},"232":{"id":232,"region":{"he":"עוטף עזה","en":"Gaza Perimeter"},"name":{"he":"עוטף עזה 232","en":"Gaza Perimeter 232"},"coverTime":15,"locations":[1273],"geometry":{"bounds":{"northeast":{"lat":31.3180281,"lng":34.4068791},"southwest":{"lat":31.30661,"lng":34.3970599}},"location":{"lat":31.31231905,"lng":34.4019695}}},"233":{"id":233,"region":{"he":"עוטף עזה","en":"Gaza Perimeter"},"name":{"he":"עוטף עזה 233","en":"Gaza Perimeter 233"},"coverTime":15,"locations":[1030,1044,1130,1408],"geometry":{"bounds":{"northeast":{"lat":31.287041,"lng":34.4521981},"southwest":{"lat":31.292549,"lng":34.421786}},"location":{"lat":31.289794999999998,"lng":34.43699205}}},"234":{"id":234,"region":{"he":"אשקלון","en":"Ashkelon"},"name":{"he":"אשקלון 234","en":"Ashkelon 234"},"coverTime":15,"locations":[71,830,1014,1456,1544,1729,1824],"geometry":{"bounds":{"northeast":{"lat":31.233266,"lng":34.436287},"southwest":{"lat":31.245069,"lng":34.3967}},"location":{"lat":31.2391675,"lng":34.4164935}}},"236":{"id":236,"region":{"he":"עוטף עזה","en":"Gaza Perimeter"},"name":{"he":"עוטף עזה 236","en":"Gaza Perimeter 236"},"coverTime":15,"locations":[698,1270,1315],"geometry":{"bounds":{"northeast":{"lat":31.2354411,"lng":34.36374800000001},"southwest":{"lat":31.233239,"lng":34.321785}},"location":{"lat":31.23434005,"lng":34.3427665}}},"237":{"id":237,"region":{"he":"עוטף עזה","en":"Gaza Perimeter"},"name":{"he":"עוטף עזה 237","en":"Gaza Perimeter 237"},"coverTime":15,"locations":[973],"geometry":{"bounds":{"northeast":{"lat":31.230621,"lng":34.287422},"southwest":{"lat":31.224588,"lng":34.28178}},"location":{"lat":31.227604499999998,"lng":34.284600999999995}}},"238":{"id":238,"region":{"he":"עוטף עזה","en":"Gaza Perimeter"},"name":{"he":"עוטף עזה 238","en":"Gaza Perimeter 238"},"coverTime":15,"locations":[63,375,586,772,833,1201,1535,1734,1771,1827],"geometry":{"bounds":{"northeast":{"lat":31.148468,"lng":35.4220719},"southwest":{"lat":31.905294,"lng":34.3075199}},"location":{"lat":31.526881000000003,"lng":34.864795900000004}}},"245":{"id":245,"region":{"he":"אשקלון","en":"Ashkelon"},"name":{"he":"אשקלון 245","en":"Ashkelon 245"},"coverTime":45,"locations":[1258,1259,1263],"geometry":{"bounds":{"northeast":{"lat":31.72175,"lng":34.6431201},"southwest":{"lat":31.733715,"lng":34.6249131}},"location":{"lat":31.727732500000002,"lng":34.634016599999995}}},"246":{"id":246,"region":{"he":"אשקלון","en":"Ashkelon"},"name":{"he":"אשקלון 246","en":"Ashkelon 246"},"coverTime":30,"locations":[228,237],"geometry":{"bounds":{"northeast":{"lat":31.7159071,"lng":34.614373},"southwest":{"lat":31.619543,"lng":34.5149351}},"location":{"lat":31.66772505,"lng":34.56465405}}},"247":{"id":247,"region":{"he":"אשקלון","en":"Ashkelon"},"name":{"he":"אשקלון 247","en":"Ashkelon 247"},"coverTime":30,"locations":[21],"geometry":{"bounds":{"northeast":{},"southwest":{}},"location":{"lat":null,"lng":null}}},"248":{"id":248,"region":{"he":"אשקלון","en":"Ashkelon"},"name":{"he":"אשקלון 248","en":"Ashkelon 248"},"coverTime":30,"locations":[397,594,938,1179,1271],"geometry":{"bounds":{"northeast":{"lat":31.6635731,"lng":34.6510301},"southwest":{"lat":31.681044,"lng":34.6122799}},"location":{"lat":31.67230855,"lng":34.631654999999995}}},"249":{"id":249,"region":{"he":"אשקלון","en":"Ashkelon"},"name":{"he":"אשקלון 249","en":"Ashkelon 249"},"coverTime":30,"locations":[631,783,845,1193,1195,1200,1268,1373,1723,1756],"geometry":{"bounds":{"northeast":{"lat":31.598692,"lng":34.734963},"southwest":{"lat":31.65281999999999,"lng":34.661814}},"location":{"lat":31.625755999999996,"lng":34.6983885}}},"250":{"id":250,"region":{"he":"אשקלון","en":"Ashkelon"},"name":{"he":"אשקלון 250","en":"Ashkelon 250"},"coverTime":30,"locations":[352,403,495,1015,1829],"geometry":{"bounds":{"northeast":{"lat":31.623907,"lng":34.624055},"southwest":{"lat":31.641985,"lng":34.572864}},"location":{"lat":31.632945999999997,"lng":34.598459500000004}}},"251":{"id":251,"region":{"he":"אשקלון","en":"Ashkelon"},"name":{"he":"אשקלון 251","en":"Ashkelon 251"},"coverTime":15,"locations":[393,484,716,1721,1830],"geometry":{"bounds":{"northeast":{"lat":31.5626951,"lng":34.6881681},"southwest":{"lat":31.5880449,"lng":34.60695}},"location":{"lat":31.57537,"lng":34.64755905}}},"252":{"id":252,"region":{"he":"אשקלון","en":"Ashkelon"},"name":{"he":"אשקלון 252","en":"Ashkelon 252"},"coverTime":15,"locations":[554,693,1657],"geometry":{"bounds":{"northeast":{"lat":31.501301,"lng":34.7105239},"southwest":{"lat":31.50163,"lng":34.641427}},"location":{"lat":31.501465500000002,"lng":34.675975449999996}}},"253":{"id":253,"region":{"he":"אשקלון","en":"Ashkelon"},"name":{"he":"אשקלון 253","en":"Ashkelon 253"},"coverTime":30,"locations":[220,645,794,1012,1272,1276,1524,1592,1710,1731,1826],"geometry":{"bounds":{"northeast":{"lat":31.4411939,"lng":34.719917},"southwest":{"lat":31.4741461,"lng":34.602625}},"location":{"lat":31.45767,"lng":34.661271}}},"254":{"id":254,"region":{"he":"אשקלון","en":"Ashkelon"},"name":{"he":"אשקלון 254","en":"Ashkelon 254"},"coverTime":30,"locations":[298,1301,1612],"geometry":{"bounds":{"northeast":{"lat":31.432141,"lng":34.613333},"southwest":{"lat":31.4179529,"lng":34.5574611}},"location":{"lat":31.425046950000002,"lng":34.58539705}}},"255":{"id":255,"region":{"he":"אשקלון","en":"Ashkelon"},"name":{"he":"אשקלון 255","en":"Ashkelon 255"},"coverTime":30,"locations":[395,457,1080,1102,1758,1797,1800,1801],"geometry":{"bounds":{"northeast":{"lat":31.374711,"lng":34.653123},"southwest":{"lat":31.39922199999999,"lng":34.5855079}},"location":{"lat":31.386966499999996,"lng":34.61931545}}},"256":{"id":256,"region":{"he":"אשקלון","en":"Ashkelon"},"name":{"he":"אשקלון 256","en":"Ashkelon 256"},"coverTime":30,"locations":[95,1514],"geometry":{"bounds":{"northeast":{"lat":31.308211,"lng":34.570615},"southwest":{"lat":31.3177399,"lng":34.5183241}},"location":{"lat":31.31297545,"lng":34.54446955}}},"257":{"id":257,"region":{"he":"אשקלון","en":"Ashkelon"},"name":{"he":"אשקלון 257","en":"Ashkelon 257"},"coverTime":30,"locations":[452,1540],"geometry":{"bounds":{"northeast":{"lat":31.207437,"lng":34.538654},"southwest":{"lat":31.2066761,"lng":34.460113}},"location":{"lat":31.207056549999997,"lng":34.4993835}}},"266":{"id":266,"region":{"he":"אשדוד","en":"Ashdod"},"name":{"he":"אשדוד 266","en":"Ashdod 266"},"coverTime":60,"locations":[451,775,892],"geometry":{"bounds":{"northeast":{"lat":31.892707,"lng":34.7744951},"southwest":{"lat":31.880149,"lng":34.7129861}},"location":{"lat":31.886428000000002,"lng":34.7437406}}},"267":{"id":267,"region":{"he":"אשדוד","en":"Ashdod"},"name":{"he":"אשדוד 267","en":"Ashdod 267"},"coverTime":60,"locations":[294,347,365,380,870,929,970,1071,1164,1497,1545,1569,1737],"geometry":{"bounds":{"northeast":{"lat":31.822013,"lng":35.160231},"southwest":{"lat":32.22001,"lng":34.7108429}},"location":{"lat":32.0210115,"lng":34.93553695}}},"268":{"id":268,"region":{"he":"אשדוד","en":"Ashdod"},"name":{"he":"אשדוד 268","en":"Ashdod 268"},"coverTime":60,"locations":[286,310,379,394,489,522,729,779,1577,1645],"geometry":{"bounds":{"northeast":{"lat":31.7756319,"lng":34.827306},"southwest":{"lat":31.8303771,"lng":34.759246}},"location":{"lat":31.8030045,"lng":34.793276}}},"271":{"id":271,"region":{"he":"אשדוד","en":"Ashdod"},"name":{"he":"אשדוד 271","en":"Ashdod 271"},"coverTime":45,"locations":[222,371,1209,1266,1358],"geometry":{"bounds":{"northeast":{"lat":31.825383,"lng":34.7021951},"southwest":{"lat":31.8203241,"lng":34.6141131}},"location":{"lat":31.822853549999998,"lng":34.6581541}}},"272":{"id":272,"region":{"he":"אשדוד","en":"Ashdod"},"name":{"he":"אשדוד 272","en":"Ashdod 272"},"coverTime":45,"locations":[200,337,482,1384,1387,1730,1799],"geometry":{"bounds":{"northeast":{"lat":31.7383529,"lng":34.704977},"southwest":{"lat":31.76532,"lng":34.646512}},"location":{"lat":31.75183645,"lng":34.6757445}}},"273":{"id":273,"region":{"he":"אשדוד","en":"Ashdod"},"name":{"he":"אשדוד 273","en":"Ashdod 273"},"coverTime":60,"locations":[268,377,510,514,731,733,862,1217],"geometry":{"bounds":{"northeast":{"lat":31.782485,"lng":34.812541},"southwest":{"lat":32.067506,"lng":34.6696039}},"location":{"lat":31.9249955,"lng":34.741072450000004}}},"275":{"id":275,"region":{"he":"אשדוד","en":"Ashdod"},"name":{"he":"אשדוד 275","en":"Ashdod 275"},"coverTime":45,"locations":[51,93,104,158,238,805,874,897,899,927,1492,1617,1808,1828],"geometry":{"bounds":{"northeast":{"lat":31.716258,"lng":34.840953},"southwest":{"lat":31.7469971,"lng":34.7100679}},"location":{"lat":31.73162755,"lng":34.77551045}}},"276":{"id":276,"region":{"he":"אשדוד","en":"Ashdod"},"name":{"he":"אשדוד 276","en":"Ashdod 276"},"coverTime":45,"locations":[1162,1168,1434,1789],"geometry":{"bounds":{"northeast":{"lat":31.7005311,"lng":34.742034},"southwest":{"lat":31.699838,"lng":34.685003}},"location":{"lat":31.70018455,"lng":34.7135185}}},"278":{"id":278,"region":{"he":"אשדוד","en":"Ashdod"},"name":{"he":"אשדוד 278","en":"Ashdod 278"},"coverTime":60,"locations":[474,528,640,901,994,1239,1357,1562,1733,1795,1810],"geometry":{"bounds":{"northeast":{"lat":31.633799,"lng":34.960507},"southwest":{"lat":31.744794,"lng":34.87216799999999}},"location":{"lat":31.689296499999998,"lng":34.9163375}}},"280":{"id":280,"region":{"he":"אשדוד","en":"Ashdod"},"name":{"he":"אשדוד 280","en":"Ashdod 280"},"coverTime":45,"locations":[176,622,628,646,1083,1241,1265,1310,1574,1583,1654],"geometry":{"bounds":{"northeast":{"lat":31.654236,"lng":34.799696},"southwest":{"lat":31.675364,"lng":34.7215809}},"location":{"lat":31.6648,"lng":34.76063845}}},"281":{"id":281,"region":{"he":"אשדוד","en":"Ashdod"},"name":{"he":"אשדוד 281","en":"Ashdod 281"},"coverTime":30,"locations":[59,105,129,533,1013,1222,1365,1610,1726,1767],"geometry":{"bounds":{"northeast":{"lat":31.5602511,"lng":35.281907},"southwest":{"lat":32.9621179,"lng":34.741235}},"location":{"lat":32.2611845,"lng":35.011571}}},"282":{"id":282,"region":{"he":"אשדוד","en":"Ashdod"},"name":{"he":"אשדוד 282","en":"Ashdod 282"},"coverTime":60,"locations":[293,328,505,999],"geometry":{"bounds":{"northeast":{"lat":31.570242,"lng":34.9034771},"southwest":{"lat":31.6438349,"lng":34.8350739}},"location":{"lat":31.60703845,"lng":34.8692755}}},"285":{"id":285,"region":{"he":"באר שבע","en":"Beersheba"},"name":{"he":"באר שבע 285","en":"Beersheba 285"},"coverTime":60,"locations":[134,203,226,251,276,326,370,972,976,1251,1748,1793],"geometry":{"bounds":{"northeast":{"lat":31.393244,"lng":34.941589},"southwest":{"lat":31.529408,"lng":34.8799769}},"location":{"lat":31.461326,"lng":34.91078295}}},"286":{"id":286,"region":{"he":"באר שבע","en":"Beersheba"},"name":{"he":"באר שבע 286","en":"Beersheba 286"},"coverTime":45,"locations":[5,6,140,146,165,345,459,541,597,931,988,991,1128,1173,1650,1743,1844],"geometry":{"bounds":{"northeast":{"lat":31.34997,"lng":34.8749061},"southwest":{"lat":31.442373,"lng":34.711234}},"location":{"lat":31.3961715,"lng":34.79307005}}},"287":{"id":287,"region":{"he":"נגב","en":"Negev"},"name":{"he":"נגב 287","en":"Negev 287"},"coverTime":90,"locations":[22,29,30,33,34,35,36,44,132,1002,1369,1821],"geometry":{"bounds":{"northeast":{"lat":31.2590039,"lng":34.892411},"southwest":{"lat":31.311334,"lng":34.8255391}},"location":{"lat":31.28516895,"lng":34.85897505}}},"288":{"id":288,"region":{"he":"באר שבע","en":"Beersheba"},"name":{"he":"באר שבע 288","en":"Beersheba 288"},"coverTime":45,"locations":[86,1098,1505,1698],"geometry":{"bounds":{"northeast":{"lat":31.325667,"lng":34.6461139},"southwest":{"lat":31.330524,"lng":34.58203810000001}},"location":{"lat":31.3280955,"lng":34.61407600000001}}},"289":{"id":289,"region":{"he":"באר שבע","en":"Beersheba"},"name":{"he":"באר שבע 289","en":"Beersheba 289"},"coverTime":45,"locations":[261,499,1841],"geometry":{"bounds":{"northeast":{"lat":31.333573,"lng":34.689452},"southwest":{"lat":31.329646,"lng":34.619986}},"location":{"lat":31.3316095,"lng":34.654719}}},"291":{"id":291,"region":{"he":"באר שבע","en":"Beersheba"},"name":{"he":"באר שבע 291","en":"Beersheba 291"},"coverTime":60,"locations":[735],"geometry":{"bounds":{"northeast":{"lat":31.243596,"lng":34.723641},"southwest":{"lat":31.234834,"lng":34.7088371}},"location":{"lat":31.239215,"lng":34.71623905}}},"292":{"id":292,"region":{"he":"באר שבע","en":"Beersheba"},"name":{"he":"באר שבע 292","en":"Beersheba 292"},"coverTime":60,"locations":[241,1100],"geometry":{"bounds":{"northeast":{"lat":31.3110787,"lng":34.8438839},"southwest":{"lat":31.2118039,"lng":34.7378901}},"location":{"lat":31.2614413,"lng":34.790887}}},"296":{"id":296,"region":{"he":"נגב","en":"Negev"},"name":{"he":"נגב 296","en":"Negev 296"},"coverTime":90,"locations":[11,13,23,159,207,705,980,981,1040,1073,1334,1374],"geometry":{"bounds":{"northeast":{"lat":31.3141279,"lng":34.968617},"southwest":{"lat":31.360674,"lng":34.8978359}},"location":{"lat":31.33740095,"lng":34.93322645}}},"297":{"id":297,"region":{"he":"נגב","en":"Negev"},"name":{"he":"נגב 297","en":"Negev 297"},"coverTime":90,"locations":[38,46,147,164,269,1190,1715],"geometry":{"bounds":{"northeast":{"lat":31.222899,"lng":34.892189},"southwest":{"lat":31.214693,"lng":34.828423}},"location":{"lat":31.218796,"lng":34.860306}}},"299":{"id":299,"region":{"he":"נגב","en":"Negev"},"name":{"he":"נגב 299","en":"Negev 299"},"coverTime":90,"locations":[24,25,39,40,42,43,136,137,157,169,171,172,173,174,442,587,627,841,864,1075,1291,1491,1495,1568,1580,1626],"geometry":{"bounds":{"northeast":{"lat":31.175194,"lng":35.2606809},"southwest":{"lat":31.2211699,"lng":34.987409}},"location":{"lat":31.19818195,"lng":35.12404495}}},"300":{"id":300,"region":{"he":"נגב","en":"Negev"},"name":{"he":"נגב 300","en":"Negev 300"},"coverTime":90,"locations":[4,37,138,142,148,1376,1377,1378,1379,1691,1845],"geometry":{"bounds":{"northeast":{},"southwest":{}},"location":{"lat":null,"lng":null}}},"301":{"id":301,"region":{"he":"נגב","en":"Negev"},"name":{"he":"נגב 301","en":"Negev 301"},"coverTime":90,"locations":[92,154,156,161,559,596,824,1598,1624,1665],"geometry":{"bounds":{"northeast":{"lat":31.0137129,"lng":35.201787},"southwest":{"lat":31.601824,"lng":34.761401}},"location":{"lat":31.30776845,"lng":34.981594}}},"302":{"id":302,"region":{"he":"נגב","en":"Negev"},"name":{"he":"נגב 302","en":"Negev 302"},"coverTime":90,"locations":[227,240,271,760,860,1121,1163,1260,1261,1380,1600,1630,1646,1656,1707,1759],"geometry":{"bounds":{"northeast":{"lat":30.79407,"lng":34.791422},"southwest":{"lat":31.049092,"lng":34.3915141}},"location":{"lat":30.921581000000003,"lng":34.59146805}}},"305":{"id":305,"region":{"he":"נגב","en":"Negev"},"name":{"he":"נגב 305","en":"Negev 305"},"coverTime":90,"locations":[1035,1143,1153,1720,1768],"geometry":{"bounds":{"northeast":{"lat":30.665401,"lng":34.8961549},"southwest":{"lat":30.886023,"lng":34.740825}},"location":{"lat":30.775712,"lng":34.81848995}}},"308":{"id":308,"region":{"he":"ערבה","en":"Negev"},"name":{"he":"ערבה 308","en":"Negev 308"},"coverTime":180,"locations":[1760],"geometry":{"bounds":{"northeast":{"lat":30.178853,"lng":35.018341},"southwest":{"lat":30.174853,"lng":35.01437110000001}},"location":{"lat":30.176853,"lng":35.016356050000006}}},"310":{"id":310,"region":{"he":"ערבה","en":"Negev"},"name":{"he":"ערבה 310","en":"Negev 310"},"coverTime":180,"locations":[188,236,529,732,787,799,997,1185,1187,1212,1332,1339,1391,1419,1424,1440,1444,1501,1548,1550,1587,1757],"geometry":{"bounds":{"northeast":{"lat":29.714613,"lng":35.3829539},"southwest":{"lat":30.940539,"lng":34.9765881}},"location":{"lat":30.327576,"lng":35.179771}}},"311":{"id":311,"region":{"he":"אילת","en":"Eilat"},"name":{"he":"אילת 311","en":"Eilat 311"},"coverTime":30,"locations":[119,122],"geometry":{"bounds":{"northeast":{"lat":29.583967,"lng":35.0087689},"southwest":{"lat":29.5769731,"lng":34.899364}},"location":{"lat":29.580470050000002,"lng":34.95406645}}}}